lagrangebench_test/__init__.py
lagrangebench_test/case_setup/__init__.py
lagrangebench_test/case_setup/case.py
lagrangebench_test/case_setup/features.py
lagrangebench_test/case_setup/partition.py
lagrangebench_test/data/__init__.py
lagrangebench_test/data/data.py
lagrangebench_test/data/utils.py
lagrangebench_test/defaults.py
lagrangebench_test/evaluate/__init__.py
lagrangebench_test/evaluate/metrics.py
lagrangebench_test/evaluate/rollout.py
lagrangebench_test/models/__init__.py
lagrangebench_test/models/base.py
lagrangebench_test/models/egnn.py
lagrangebench_test/models/gns.py
lagrangebench_test/models/linear.py
lagrangebench_test/models/painn.py
lagrangebench_test/models/segnn.py
lagrangebench_test/models/utils.py
lagrangebench_test/train/__init__.py
lagrangebench_test/train/strats.py
lagrangebench_test/train/trainer.py
lagrangebench_test/utils.py
lagrangebench_test-0.0.2.dist-info/LICENSE
lagrangebench_test-0.0.2.dist-info/METADATA
lagrangebench_test-0.0.2.dist-info/WHEEL
lagrangebench_test-0.0.2.dist-info/RECORD
