Metadata-Version: 2.1
Name: lagrangebench-test
Version: 0.0.2
Summary: LagrangeBench: A Lagrangian Fluid Mechanics Benchmarking Suite
License: MIT
Author: Artur Toshev
Author-email: artur.toshev@tum.de
Requires-Python: >=3.9,<4.0
Classifier: License :: OSI Approved :: MIT License
Classifier: Programming Language :: Python :: 3
Classifier: Programming Language :: Python :: 3.9
Classifier: Programming Language :: Python :: 3.10
Classifier: Programming Language :: Python :: 3.11
Requires-Dist: PyYAML (>=6.0,<7.0)
Requires-Dist: cloudpickle (>=2.2.1,<3.0.0)
Requires-Dist: dm-haiku (>=0.0.10,<0.0.11)
Requires-Dist: e3nn-jax (==0.17.0)
Requires-Dist: gdown (>=4.7.1,<5.0.0)
Requires-Dist: h5py (>=3.8.0,<4.0.0)
Requires-Dist: jax (>=0.4.10,<0.5.0)
Requires-Dist: jax-md (==0.2.3)
Requires-Dist: jmp (>=0.0.4,<0.0.5)
Requires-Dist: jraph (==0.0.6.dev0)
Requires-Dist: matscipy (>=0.8.0,<0.9.0)
Requires-Dist: numpy (>=1.24.3,<2.0.0)
Requires-Dist: optax (==0.1.5)
Requires-Dist: ott-jax (>=0.4.0,<0.5.0)
Requires-Dist: pyvista (>=0.38.6,<0.39.0)
Requires-Dist: torch (==1.13.1)
Requires-Dist: wandb (>=0.15.1,<0.16.0)
